{
  "project_info": {
    "project_number": "932083352411",
    "project_id": "tripledger-9835b",
    "storage_bucket": "tripledger-9835b.firebasestorage.app"
  },
  "client": [
    {
      "client_info": {
        "mobilesdk_app_id": "1:932083352411:android:0bda26f494655cf5b3d07e",
        "android_client_info": {
          "package_name": "com.tripledger"
        }
      },
      "oauth_client": [
        {
          "client_id": "932083352411-284h9cciarlren25kl322t8lhtv4rgbm.apps.googleusercontent.com",
          "client_type": 1,
          "android_info": {
            "package_name": "com.tripledger",
            "certificate_hash": "5e8f16062ea3cd2c4a0d547876baa6f38cabf625"
          }
        },
        {
          "client_id": "932083352411-sjth69a4u9d2qg6odgoe8shfk9mdemi8.apps.googleusercontent.com",
          "client_type": 3
        }
      ],
      "api_key": [
        {
          "current_key": "AIzaSyAn5T8DQxfihhg__DuFFLRK7A4qLI85zpU"
        }
      ],
      "services": {
        "appinvite_service": {
          "other_platform_oauth_client": [
            {
              "client_id": "932083352411-sjth69a4u9d2qg6odgoe8shfk9mdemi8.apps.googleusercontent.com",
              "client_type": 3
            }
          ]
        }
      }
    }
  ],
  "configuration_version": "1"
}